{
  "task_id": "OpenBox",
  "num_objectives": 2,
  "num_constraints": 0,
  "ref_point": [
    0.2,
    0.1
  ],
  "meta_info": {},
  "global_start_time": "2024-12-16T03:52:15.905148",
  "observations": [
    {
      "config": {
        "fi__repair_level": 0.55,
        "model__max_depth": 3,
        "model__min_data_in_leaf": 100,
        "model__n_estimators": 50,
        "model__num_leaves": 20,
        "model__verbosity": -1
      },
      "objectives": [
        0.18891820580474938,
        0.033835389690431206
      ],
      "constraints": null,
      "trial_state": 0,
      "elapsed_time": 2.941251516342163,
      "create_time": "2024-12-16T03:52:29.002525",
      "extra_info": {
        "original_objectives": [
          0.18891820580474938,
          0.033835389690431206
        ],
        "reversed_objectives": [
          0.8110817941952506,
          0.9661646103095688
        ],
        "exp_config_objectives": [
          {
            "name": "objective_1",
            "metric": "F1",
            "group": "overall",
            "weight": 0.25
          },
          {
            "name": "objective_2",
            "metric": "Equalized_Odds_TPR",
            "group": "SEX&RAC1P",
            "weight": 0.75
          }
        ]
      }
    },
    {
      "config": {
        "fi__repair_level": 0.4312958422138021,
        "model__max_depth": 9,
        "model__min_data_in_leaf": 228,
        "model__n_estimators": 50,
        "model__num_leaves": 871,
        "model__verbosity": -1
      },
      "objectives": [
        0.19362678908992703,
        0.04075695854806716
      ],
      "constraints": null,
      "trial_state": 0,
      "elapsed_time": 2.865830421447754,
      "create_time": "2024-12-16T03:53:19.433908",
      "extra_info": {
        "original_objectives": [
          0.19362678908992703,
          0.04075695854806716
        ],
        "reversed_objectives": [
          0.806373210910073,
          0.9592430414519328
        ],
        "exp_config_objectives": [
          {
            "name": "objective_1",
            "metric": "F1",
            "group": "overall",
            "weight": 0.25
          },
          {
            "name": "objective_2",
            "metric": "Equalized_Odds_TPR",
            "group": "SEX&RAC1P",
            "weight": 0.75
          }
        ]
      }
    },
    {
      "config": {
        "fi__repair_level": 0.1275763293837294,
        "model__max_depth": 3,
        "model__min_data_in_leaf": 1000,
        "model__n_estimators": 100,
        "model__num_leaves": 871,
        "model__verbosity": -1
      },
      "objectives": [
        0.20448332422088578,
        0.03940927180305931
      ],
      "constraints": null,
      "trial_state": 0,
      "elapsed_time": 2.921285629272461,
      "create_time": "2024-12-16T04:00:40.665820",
      "extra_info": {
        "original_objectives": [
          0.20448332422088578,
          0.03940927180305931
        ],
        "reversed_objectives": [
          0.7955166757791142,
          0.9605907281969407
        ],
        "exp_config_objectives": [
          {
            "name": "objective_1",
            "metric": "F1",
            "group": "overall",
            "weight": 0.25
          },
          {
            "name": "objective_2",
            "metric": "Equalized_Odds_TPR",
            "group": "SEX&RAC1P",
            "weight": 0.75
          }
        ]
      }
    },
    {
      "config": {
        "fi__repair_level": 0.7431862229987359,
        "model__max_depth": -1,
        "model__min_data_in_leaf": 1000,
        "model__n_estimators": 500,
        "model__num_leaves": 2574,
        "model__verbosity": -1
      },
      "objectives": [
        0.20183982683982682,
        0.02527499618468476
      ],
      "constraints": null,
      "trial_state": 0,
      "elapsed_time": 5.871777534484863,
      "create_time": "2024-12-16T03:52:51.213030",
      "extra_info": {
        "original_objectives": [
          0.20183982683982682,
          0.02527499618468476
        ],
        "reversed_objectives": [
          0.7981601731601732,
          0.9747250038153152
        ],
        "exp_config_objectives": [
          {
            "name": "objective_1",
            "metric": "F1",
            "group": "overall",
            "weight": 0.25
          },
          {
            "name": "objective_2",
            "metric": "Equalized_Odds_TPR",
            "group": "SEX&RAC1P",
            "weight": 0.75
          }
        ]
      }
    },
    {
      "config": {
        "fi__repair_level": 0.5791408377261522,
        "model__max_depth": 3,
        "model__min_data_in_leaf": 614,
        "model__n_estimators": 50,
        "model__num_leaves": 3000,
        "model__verbosity": -1
      },
      "objectives": [
        0.19585987261146498,
        0.02520925536785512
      ],
      "constraints": null,
      "trial_state": 0,
      "elapsed_time": 2.7319765090942383,
      "create_time": "2024-12-16T03:53:28.357154",
      "extra_info": {
        "original_objectives": [
          0.19585987261146498,
          0.02520925536785512
        ],
        "reversed_objectives": [
          0.804140127388535,
          0.9747907446321449
        ],
        "exp_config_objectives": [
          {
            "name": "objective_1",
            "metric": "F1",
            "group": "overall",
            "weight": 0.25
          },
          {
            "name": "objective_2",
            "metric": "Equalized_Odds_TPR",
            "group": "SEX&RAC1P",
            "weight": 0.75
          }
        ]
      }
    },
    {
      "config": {
        "fi__repair_level": 0.13263587959705658,
        "model__max_depth": 6,
        "model__min_data_in_leaf": 485,
        "model__n_estimators": 500,
        "model__num_leaves": 3000,
        "model__verbosity": -1
      },
      "objectives": [
        0.19661848922825198,
        0.054891234166441705
      ],
      "constraints": null,
      "trial_state": 0,
      "elapsed_time": 5.064872741699219,
      "create_time": "2024-12-16T04:00:32.788698",
      "extra_info": {
        "original_objectives": [
          0.19661848922825198,
          0.054891234166441705
        ],
        "reversed_objectives": [
          0.803381510771748,
          0.9451087658335583
        ],
        "exp_config_objectives": [
          {
            "name": "objective_1",
            "metric": "F1",
            "group": "overall",
            "weight": 0.25
          },
          {
            "name": "objective_2",
            "metric": "Equalized_Odds_TPR",
            "group": "SEX&RAC1P",
            "weight": 0.75
          }
        ]
      }
    },
    {
      "config": {
        "fi__repair_level": 0.5349017053012204,
        "model__max_depth": 4,
        "model__min_data_in_leaf": 1000,
        "model__n_estimators": 500,
        "model__num_leaves": 1722,
        "model__verbosity": -1
      },
      "objectives": [
        0.20097508125677144,
        0.029303969101816096
      ],
      "constraints": null,
      "trial_state": 0,
      "elapsed_time": 3.920365810394287,
      "create_time": "2024-12-16T04:26:00.442822",
      "extra_info": {
        "original_objectives": [
          0.20097508125677144,
          0.029303969101816096
        ],
        "reversed_objectives": [
          0.7990249187432286,
          0.9706960308981839
        ],
        "exp_config_objectives": [
          {
            "name": "objective_1",
            "metric": "F1",
            "group": "overall",
            "weight": 0.25
          },
          {
            "name": "objective_2",
            "metric": "Equalized_Odds_TPR",
            "group": "SEX&RAC1P",
            "weight": 0.75
          }
        ]
      }
    },
    {
      "config": {
        "fi__repair_level": 0.28606240715561226,
        "model__max_depth": 7,
        "model__min_data_in_leaf": 1000,
        "model__n_estimators": 200,
        "model__num_leaves": 871,
        "model__verbosity": -1
      },
      "objectives": [
        0.20481927710843373,
        0.04555838606294682
      ],
      "constraints": null,
      "trial_state": 0,
      "elapsed_time": 3.3762598037719727,
      "create_time": "2024-12-16T04:26:09.915384",
      "extra_info": {
        "original_objectives": [
          0.20481927710843373,
          0.04555838606294682
        ],
        "reversed_objectives": [
          0.7951807228915663,
          0.9544416139370532
        ],
        "exp_config_objectives": [
          {
            "name": "objective_1",
            "metric": "F1",
            "group": "overall",
            "weight": 0.25
          },
          {
            "name": "objective_2",
            "metric": "Equalized_Odds_TPR",
            "group": "SEX&RAC1P",
            "weight": 0.75
          }
        ]
      }
    },
    {
      "config": {
        "fi__repair_level": 0.2531872715704211,
        "model__max_depth": 7,
        "model__min_data_in_leaf": 228,
        "model__n_estimators": 500,
        "model__num_leaves": 871,
        "model__verbosity": -1
      },
      "objectives": [
        0.19825470411780743,
        0.04089548384067243
      ],
      "constraints": null,
      "trial_state": 0,
      "elapsed_time": 6.065123081207275,
      "create_time": "2024-12-16T04:38:19.047998",
      "extra_info": {
        "original_objectives": [
          0.19825470411780743,
          0.04089548384067243
        ],
        "reversed_objectives": [
          0.8017452958821926,
          0.9591045161593276
        ],
        "exp_config_objectives": [
          {
            "name": "objective_1",
            "metric": "F1",
            "group": "overall",
            "weight": 0.25
          },
          {
            "name": "objective_2",
            "metric": "Equalized_Odds_TPR",
            "group": "SEX&RAC1P",
            "weight": 0.75
          }
        ]
      }
    },
    {
      "config": {
        "fi__repair_level": 0.38835909456887885,
        "model__max_depth": 4,
        "model__min_data_in_leaf": 1000,
        "model__n_estimators": 200,
        "model__num_leaves": 20,
        "model__verbosity": -1
      },
      "objectives": [
        0.2051352089593007,
        0.043438244720190644
      ],
      "constraints": null,
      "trial_state": 0,
      "elapsed_time": 3.151599645614624,
      "create_time": "2024-12-16T04:38:06.116386",
      "extra_info": {
        "original_objectives": [
          0.2051352089593007,
          0.043438244720190644
        ],
        "reversed_objectives": [
          0.7948647910406993,
          0.9565617552798094
        ],
        "exp_config_objectives": [
          {
            "name": "objective_1",
            "metric": "F1",
            "group": "overall",
            "weight": 0.25
          },
          {
            "name": "objective_2",
            "metric": "Equalized_Odds_TPR",
            "group": "SEX&RAC1P",
            "weight": 0.75
          }
        ]
      }
    },
    {
      "config": {
        "fi__repair_level": 0.97058316802146,
        "model__max_depth": 6,
        "model__min_data_in_leaf": 614,
        "model__n_estimators": 50,
        "model__num_leaves": 20,
        "model__verbosity": -1
      },
      "objectives": [
        0.19828510182207937,
        0.026549898453916865
      ],
      "constraints": null,
      "trial_state": 0,
      "elapsed_time": 2.5755255222320557,
      "create_time": "2024-12-16T04:51:22.230248",
      "extra_info": {
        "original_objectives": [
          0.19828510182207937,
          0.026549898453916865
        ],
        "reversed_objectives": [
          0.8017148981779206,
          0.9734501015460831
        ],
        "exp_config_objectives": [
          {
            "name": "objective_1",
            "metric": "F1",
            "group": "overall",
            "weight": 0.25
          },
          {
            "name": "objective_2",
            "metric": "Equalized_Odds_TPR",
            "group": "SEX&RAC1P",
            "weight": 0.75
          }
        ]
      }
    },
    {
      "config": {
        "fi__repair_level": 0.8849509003169245,
        "model__max_depth": 3,
        "model__min_data_in_leaf": 357,
        "model__n_estimators": 500,
        "model__num_leaves": 3000,
        "model__verbosity": -1
      },
      "objectives": [
        0.1957503320053121,
        0.029944942065905145
      ],
      "constraints": null,
      "trial_state": 0,
      "elapsed_time": 3.556528091430664,
      "create_time": "2024-12-16T04:58:07.319244",
      "extra_info": {
        "original_objectives": [
          0.1957503320053121,
          0.029944942065905145
        ],
        "reversed_objectives": [
          0.8042496679946879,
          0.9700550579340949
        ],
        "exp_config_objectives": [
          {
            "name": "objective_1",
            "metric": "F1",
            "group": "overall",
            "weight": 0.25
          },
          {
            "name": "objective_2",
            "metric": "Equalized_Odds_TPR",
            "group": "SEX&RAC1P",
            "weight": 0.75
          }
        ]
      }
    },
    {
      "config": {
        "fi__repair_level": 0.5140921484825386,
        "model__max_depth": 7,
        "model__min_data_in_leaf": 742,
        "model__n_estimators": 500,
        "model__num_leaves": 1722,
        "model__verbosity": -1
      },
      "objectives": [
        0.20291419320021586,
        0.02789054153997861
      ],
      "constraints": null,
      "trial_state": 0,
      "elapsed_time": 4.198218107223511,
      "create_time": "2024-12-16T04:51:33.872638",
      "extra_info": {
        "original_objectives": [
          0.20291419320021586,
          0.02789054153997861
        ],
        "reversed_objectives": [
          0.7970858067997841,
          0.9721094584600214
        ],
        "exp_config_objectives": [
          {
            "name": "objective_1",
            "metric": "F1",
            "group": "overall",
            "weight": 0.25
          },
          {
            "name": "objective_2",
            "metric": "Equalized_Odds_TPR",
            "group": "SEX&RAC1P",
            "weight": 0.75
          }
        ]
      }
    },
    {
      "config": {
        "fi__repair_level": 0.6081802868949397,
        "model__max_depth": 8,
        "model__min_data_in_leaf": 871,
        "model__n_estimators": 500,
        "model__num_leaves": 20,
        "model__verbosity": -1
      },
      "objectives": [
        0.2043419267299864,
        0.03163542021295329
      ],
      "constraints": null,
      "trial_state": 0,
      "elapsed_time": 4.682462930679321,
      "create_time": "2024-12-16T04:57:58.419444",
      "extra_info": {
        "original_objectives": [
          0.2043419267299864,
          0.03163542021295329
        ],
        "reversed_objectives": [
          0.7956580732700136,
          0.9683645797870467
        ],
        "exp_config_objectives": [
          {
            "name": "objective_1",
            "metric": "F1",
            "group": "overall",
            "weight": 0.25
          },
          {
            "name": "objective_2",
            "metric": "Equalized_Odds_TPR",
            "group": "SEX&RAC1P",
            "weight": 0.75
          }
        ]
      }
    },
    {
      "config": {
        "fi__repair_level": 0.9041815899393646,
        "model__max_depth": 3,
        "model__min_data_in_leaf": 357,
        "model__n_estimators": 500,
        "model__num_leaves": 2574,
        "model__verbosity": -1
      },
      "objectives": [
        0.1957503320053121,
        0.029944942065905145
      ],
      "constraints": null,
      "trial_state": 0,
      "elapsed_time": 3.5866360664367676,
      "create_time": "2024-12-16T05:17:47.857967",
      "extra_info": {
        "original_objectives": [
          0.1957503320053121,
          0.029944942065905145
        ],
        "reversed_objectives": [
          0.8042496679946879,
          0.9700550579340949
        ],
        "exp_config_objectives": [
          {
            "name": "objective_1",
            "metric": "F1",
            "group": "overall",
            "weight": 0.25
          },
          {
            "name": "objective_2",
            "metric": "Equalized_Odds_TPR",
            "group": "SEX&RAC1P",
            "weight": 0.75
          }
        ]
      }
    },
    {
      "config": {
        "fi__repair_level": 0.8568116817337165,
        "model__max_depth": 3,
        "model__min_data_in_leaf": 614,
        "model__n_estimators": 50,
        "model__num_leaves": 3000,
        "model__verbosity": -1
      },
      "objectives": [
        0.19585987261146498,
        0.02520925536785512
      ],
      "constraints": null,
      "trial_state": 0,
      "elapsed_time": 2.5413777828216553,
      "create_time": "2024-12-16T05:14:05.019004",
      "extra_info": {
        "original_objectives": [
          0.19585987261146498,
          0.02520925536785512
        ],
        "reversed_objectives": [
          0.804140127388535,
          0.9747907446321449
        ],
        "exp_config_objectives": [
          {
            "name": "objective_1",
            "metric": "F1",
            "group": "overall",
            "weight": 0.25
          },
          {
            "name": "objective_2",
            "metric": "Equalized_Odds_TPR",
            "group": "SEX&RAC1P",
            "weight": 0.75
          }
        ]
      }
    },
    {
      "config": {
        "fi__repair_level": 0.9352070531025923,
        "model__max_depth": 9,
        "model__min_data_in_leaf": 228,
        "model__n_estimators": 200,
        "model__num_leaves": 1297,
        "model__verbosity": -1
      },
      "objectives": [
        0.1894793344068706,
        0.028742824272448786
      ],
      "constraints": null,
      "trial_state": 0,
      "elapsed_time": 4.221289157867432,
      "create_time": "2024-12-16T05:14:16.716570",
      "extra_info": {
        "original_objectives": [
          0.1894793344068706,
          0.028742824272448786
        ],
        "reversed_objectives": [
          0.8105206655931294,
          0.9712571757275512
        ],
        "exp_config_objectives": [
          {
            "name": "objective_1",
            "metric": "F1",
            "group": "overall",
            "weight": 0.25
          },
          {
            "name": "objective_2",
            "metric": "Equalized_Odds_TPR",
            "group": "SEX&RAC1P",
            "weight": 0.75
          }
        ]
      }
    },
    {
      "config": {
        "fi__repair_level": 0.5727045400925465,
        "model__max_depth": 3,
        "model__min_data_in_leaf": 100,
        "model__n_estimators": 50,
        "model__num_leaves": 445,
        "model__verbosity": -1
      },
      "objectives": [
        0.18891820580474938,
        0.033835389690431206
      ],
      "constraints": null,
      "trial_state": 0,
      "elapsed_time": 2.735255718231201,
      "create_time": "2024-12-16T05:18:07.054118",
      "extra_info": {
        "original_objectives": [
          0.18891820580474938,
          0.033835389690431206
        ],
        "reversed_objectives": [
          0.8110817941952506,
          0.9661646103095688
        ],
        "exp_config_objectives": [
          {
            "name": "objective_1",
            "metric": "F1",
            "group": "overall",
            "weight": 0.25
          },
          {
            "name": "objective_2",
            "metric": "Equalized_Odds_TPR",
            "group": "SEX&RAC1P",
            "weight": 0.75
          }
        ]
      }
    },
    {
      "config": {
        "fi__repair_level": 0.5634842464838977,
        "model__max_depth": 9,
        "model__min_data_in_leaf": 614,
        "model__n_estimators": 100,
        "model__num_leaves": 2148,
        "model__verbosity": -1
      },
      "objectives": [
        0.19699005643644185,
        0.027963326015754242
      ],
      "constraints": null,
      "trial_state": 0,
      "elapsed_time": 3.111557722091675,
      "create_time": "2024-12-16T05:25:32.251753",
      "extra_info": {
        "original_objectives": [
          0.19699005643644185,
          0.027963326015754242
        ],
        "reversed_objectives": [
          0.8030099435635581,
          0.9720366739842458
        ],
        "exp_config_objectives": [
          {
            "name": "objective_1",
            "metric": "F1",
            "group": "overall",
            "weight": 0.25
          },
          {
            "name": "objective_2",
            "metric": "Equalized_Odds_TPR",
            "group": "SEX&RAC1P",
            "weight": 0.75
          }
        ]
      }
    },
    {
      "config": {
        "fi__repair_level": 0.752389768162221,
        "model__max_depth": 9,
        "model__min_data_in_leaf": 614,
        "model__n_estimators": 500,
        "model__num_leaves": 1297,
        "model__verbosity": -1
      },
      "objectives": [
        0.20010787486515647,
        0.031708204688728925
      ],
      "constraints": null,
      "trial_state": 0,
      "elapsed_time": 5.398297548294067,
      "create_time": "2024-12-16T05:25:44.565744",
      "extra_info": {
        "original_objectives": [
          0.20010787486515647,
          0.031708204688728925
        ],
        "reversed_objectives": [
          0.7998921251348435,
          0.9682917953112711
        ],
        "exp_config_objectives": [
          {
            "name": "objective_1",
            "metric": "F1",
            "group": "overall",
            "weight": 0.25
          },
          {
            "name": "objective_2",
            "metric": "Equalized_Odds_TPR",
            "group": "SEX&RAC1P",
            "weight": 0.75
          }
        ]
      }
    },
    {
      "config": {
        "fi__repair_level": 0.5500000000000002,
        "model__max_depth": 3,
        "model__min_data_in_leaf": 485,
        "model__n_estimators": 50,
        "model__num_leaves": 20,
        "model__verbosity": -1
      },
      "objectives": [
        0.19787798408488066,
        0.027329396710611298
      ],
      "constraints": null,
      "trial_state": 0,
      "elapsed_time": 2.685048818588257,
      "create_time": "2024-12-16T05:34:06.899624",
      "extra_info": {
        "original_objectives": [
          0.19787798408488066,
          0.027329396710611298
        ],
        "reversed_objectives": [
          0.8021220159151193,
          0.9726706032893887
        ],
        "exp_config_objectives": [
          {
            "name": "objective_1",
            "metric": "F1",
            "group": "overall",
            "weight": 0.25
          },
          {
            "name": "objective_2",
            "metric": "Equalized_Odds_TPR",
            "group": "SEX&RAC1P",
            "weight": 0.75
          }
        ]
      }
    },
    {
      "config": {
        "fi__repair_level": 0.6728284025914086,
        "model__max_depth": 9,
        "model__min_data_in_leaf": 100,
        "model__n_estimators": 200,
        "model__num_leaves": 871,
        "model__verbosity": -1
      },
      "objectives": [
        0.18921832884097034,
        0.03701207987509236
      ],
      "constraints": null,
      "trial_state": 0,
      "elapsed_time": 4.65123987197876,
      "create_time": "2024-12-16T05:41:12.639525",
      "extra_info": {
        "original_objectives": [
          0.18921832884097034,
          0.03701207987509236
        ],
        "reversed_objectives": [
          0.8107816711590297,
          0.9629879201249076
        ],
        "exp_config_objectives": [
          {
            "name": "objective_1",
            "metric": "F1",
            "group": "overall",
            "weight": 0.25
          },
          {
            "name": "objective_2",
            "metric": "Equalized_Odds_TPR",
            "group": "SEX&RAC1P",
            "weight": 0.75
          }
        ]
      }
    },
    {
      "config": {
        "fi__repair_level": 0.9577576042493091,
        "model__max_depth": 3,
        "model__min_data_in_leaf": 228,
        "model__n_estimators": 50,
        "model__num_leaves": 3000,
        "model__verbosity": -1
      },
      "objectives": [
        0.18938992042440317,
        0.02810889496730562
      ],
      "constraints": null,
      "trial_state": 0,
      "elapsed_time": 2.501315116882324,
      "create_time": "2024-12-16T05:34:16.739850",
      "extra_info": {
        "original_objectives": [
          0.18938992042440317,
          0.02810889496730562
        ],
        "reversed_objectives": [
          0.8106100795755968,
          0.9718911050326944
        ],
        "exp_config_objectives": [
          {
            "name": "objective_1",
            "metric": "F1",
            "group": "overall",
            "weight": 0.25
          },
          {
            "name": "objective_2",
            "metric": "Equalized_Odds_TPR",
            "group": "SEX&RAC1P",
            "weight": 0.75
          }
        ]
      }
    },
    {
      "config": {
        "fi__repair_level": 0.47294000118404145,
        "model__max_depth": 3,
        "model__min_data_in_leaf": 228,
        "model__n_estimators": 500,
        "model__num_leaves": 2574,
        "model__verbosity": -1
      },
      "objectives": [
        0.19113273857799407,
        0.04669476303957354
      ],
      "constraints": null,
      "trial_state": 0,
      "elapsed_time": 3.722869396209717,
      "create_time": "2024-12-16T05:43:33.979788",
      "extra_info": {
        "original_objectives": [
          0.19113273857799407,
          0.04669476303957354
        ],
        "reversed_objectives": [
          0.8088672614220059,
          0.9533052369604265
        ],
        "exp_config_objectives": [
          {
            "name": "objective_1",
            "metric": "F1",
            "group": "overall",
            "weight": 0.25
          },
          {
            "name": "objective_2",
            "metric": "Equalized_Odds_TPR",
            "group": "SEX&RAC1P",
            "weight": 0.75
          }
        ]
      }
    },
    {
      "config": {
        "fi__repair_level": 0.8614450376225876,
        "model__max_depth": 8,
        "model__min_data_in_leaf": 1000,
        "model__n_estimators": 200,
        "model__num_leaves": 1722,
        "model__verbosity": -1
      },
      "objectives": [
        0.2041203578205476,
        0.02619301973398447
      ],
      "constraints": null,
      "trial_state": 0,
      "elapsed_time": 3.2256834506988525,
      "create_time": "2024-12-16T05:47:15.040002",
      "extra_info": {
        "original_objectives": [
          0.2041203578205476,
          0.02619301973398447
        ],
        "reversed_objectives": [
          0.7958796421794524,
          0.9738069802660155
        ],
        "exp_config_objectives": [
          {
            "name": "objective_1",
            "metric": "F1",
            "group": "overall",
            "weight": 0.25
          },
          {
            "name": "objective_2",
            "metric": "Equalized_Odds_TPR",
            "group": "SEX&RAC1P",
            "weight": 0.75
          }
        ]
      }
    },
    {
      "config": {
        "fi__repair_level": 0.7299476737247859,
        "model__max_depth": 4,
        "model__min_data_in_leaf": 100,
        "model__n_estimators": 50,
        "model__num_leaves": 20,
        "model__verbosity": -1
      },
      "objectives": [
        0.18865924748277685,
        0.034046699458812224
      ],
      "constraints": null,
      "trial_state": 0,
      "elapsed_time": 2.742248058319092,
      "create_time": "2024-12-16T05:49:56.502675",
      "extra_info": {
        "original_objectives": [
          0.18865924748277685,
          0.034046699458812224
        ],
        "reversed_objectives": [
          0.8113407525172232,
          0.9659533005411878
        ],
        "exp_config_objectives": [
          {
            "name": "objective_1",
            "metric": "F1",
            "group": "overall",
            "weight": 0.25
          },
          {
            "name": "objective_2",
            "metric": "Equalized_Odds_TPR",
            "group": "SEX&RAC1P",
            "weight": 0.75
          }
        ]
      }
    },
    {
      "config": {
        "fi__repair_level": 0.4998287349659458,
        "model__max_depth": 9,
        "model__min_data_in_leaf": 614,
        "model__n_estimators": 100,
        "model__num_leaves": 445,
        "model__verbosity": -1
      },
      "objectives": [
        0.19880661784648768,
        0.03997746029137261
      ],
      "constraints": null,
      "trial_state": 0,
      "elapsed_time": 3.175494909286499,
      "create_time": "2024-12-16T05:41:01.144898",
      "extra_info": {
        "original_objectives": [
          0.19880661784648768,
          0.03997746029137261
        ],
        "reversed_objectives": [
          0.8011933821535123,
          0.9600225397086274
        ],
        "exp_config_objectives": [
          {
            "name": "objective_1",
            "metric": "F1",
            "group": "overall",
            "weight": 0.25
          },
          {
            "name": "objective_2",
            "metric": "Equalized_Odds_TPR",
            "group": "SEX&RAC1P",
            "weight": 0.75
          }
        ]
      }
    },
    {
      "config": {
        "fi__repair_level": 0.8737714592557919,
        "model__max_depth": 3,
        "model__min_data_in_leaf": 100,
        "model__n_estimators": 200,
        "model__num_leaves": 871,
        "model__verbosity": -1
      },
      "objectives": [
        0.18630573248407645,
        0.040691217731237406
      ],
      "constraints": null,
      "trial_state": 0,
      "elapsed_time": 2.9071574211120605,
      "create_time": "2024-12-16T05:43:43.182494",
      "extra_info": {
        "original_objectives": [
          0.18630573248407645,
          0.040691217731237406
        ],
        "reversed_objectives": [
          0.8136942675159236,
          0.9593087822687626
        ],
        "exp_config_objectives": [
          {
            "name": "objective_1",
            "metric": "F1",
            "group": "overall",
            "weight": 0.25
          },
          {
            "name": "objective_2",
            "metric": "Equalized_Odds_TPR",
            "group": "SEX&RAC1P",
            "weight": 0.75
          }
        ]
      }
    },
    {
      "config": {
        "fi__repair_level": 0.9352070531025923,
        "model__max_depth": 9,
        "model__min_data_in_leaf": 100,
        "model__n_estimators": 50,
        "model__num_leaves": 2148,
        "model__verbosity": -1
      },
      "objectives": [
        0.18774966711051932,
        0.04231595506145602
      ],
      "constraints": null,
      "trial_state": 0,
      "elapsed_time": 3.1172099113464355,
      "create_time": "2024-12-16T05:50:06.894064",
      "extra_info": {
        "original_objectives": [
          0.18774966711051932,
          0.04231595506145602
        ],
        "reversed_objectives": [
          0.8122503328894807,
          0.957684044938544
        ],
        "exp_config_objectives": [
          {
            "name": "objective_1",
            "metric": "F1",
            "group": "overall",
            "weight": 0.25
          },
          {
            "name": "objective_2",
            "metric": "Equalized_Odds_TPR",
            "group": "SEX&RAC1P",
            "weight": 0.75
          }
        ]
      }
    },
    {
      "config": {
        "fi__repair_level": 0.7943842261466387,
        "model__max_depth": 4,
        "model__min_data_in_leaf": 100,
        "model__n_estimators": 50,
        "model__num_leaves": 1722,
        "model__verbosity": -1
      },
      "objectives": [
        0.18865924748277685,
        0.034046699458812224
      ],
      "constraints": null,
      "trial_state": 0,
      "elapsed_time": 2.6262755393981934,
      "create_time": "2024-12-16T05:47:04.420287",
      "extra_info": {
        "original_objectives": [
          0.18865924748277685,
          0.034046699458812224
        ],
        "reversed_objectives": [
          0.8113407525172232,
          0.9659533005411878
        ],
        "exp_config_objectives": [
          {
            "name": "objective_1",
            "metric": "F1",
            "group": "overall",
            "weight": 0.25
          },
          {
            "name": "objective_2",
            "metric": "Equalized_Odds_TPR",
            "group": "SEX&RAC1P",
            "weight": 0.75
          }
        ]
      }
    }
  ]
}